[
    {
        "name": "maborak",
        "libraries": [
            {
                "name": "maborak",
                "full": "gulliver/js/maborak/core/maborak.old.js",
                "mini": "gulliver/js/maborak/core/maborak.old.js",
                "minify": true
            },
            {
                "name": "common",
                "full": "gulliver/js/common/core/common.js",
                "mini": "gulliver/js/common/core/common.js",
                "minify": true
            },
            {
                "name": "effects",
                "full": "gulliver/js/common/core/effects.js",
                "mini": "gulliver/js/common/core/effects.js",
                "minify": true
            },
            {
                "name": "webResource",
                "full": "gulliver/js/common/core/webResource.js",
                "mini": "gulliver/js/common/core/webResource.js",
                "minify": true
            },
            {
                "name": "dveditor",
                "full": "gulliver/js/dveditor/core/dveditor.js",
                "mini": "gulliver/js/dveditor/core/dveditor.js",
                "minify": true
            },
            {
                "name": "tree",
                "full": "gulliver/js/common/tree/tree.js",
                "mini": "gulliver/js/common/tree/tree.js",
                "minify": true
            },
            {
                "name": "json",
                "full": "gulliver/js/json/core/json.js",
                "mini": "gulliver/js/json/core/json.js",
                "minify": true
            },
            {
                "name": "form",
                "full": "gulliver/js/form/core/form.js",
                "mini": "gulliver/js/form/core/form.js",
                "minify": true
            },
            {
                "name": "pagedTable",
                "full": "gulliver/js/form/core/pagedTable.js",
                "mini": "gulliver/js/form/core/pagedTable.js",
                "minify": true
            },
            {
                "name": "grid",
                "full": "gulliver/js/grid/core/grid.js",
                "mini": "gulliver/js/grid/core/grid.js",
                "minify": true
            },
            {
                "name": "js-calendar",
                "full": "gulliver/js/widgets/js-calendar/js-calendar.js",
                "mini": "gulliver/js/widgets/js-calendar/js-calendar.js",
                "minify": true
            },
            {
                "name": "bsn.AutoSuggest",
                "full": "gulliver/js/widgets/suggest/bsn.AutoSuggest_2.1.3.js",
                "mini": "gulliver/js/widgets/suggest/bsn.AutoSuggest_2.1.3.js",
                "minify": true
            },
            {
                "name": "pmtooltip",
                "full": "gulliver/js/widgets/tooltip/pmtooltip.js",
                "mini": "gulliver/js/widgets/tooltip/pmtooltip.js",
                "minify": true
            }
        ],
        "build" : true,
        "build_js_to" : "gulliver/js/maborak/core/"
    },
    {
        "name": "maborak.loader",
        "libraries": [
            {
                "name": "module.panel",
                "full": "gulliver/js/maborak/core/module.panel.js",
                "mini": "gulliver/js/maborak/core/module.panel.js",
                "minify": true
            },
            {
                "name": "module.validator",
                "full": "gulliver/js/maborak/core/module.validator.js",
                "mini": "gulliver/js/maborak/core/module.validator.js",
                "minify": true
            },
            {
                "name": "module.app",
                "full": "gulliver/js/maborak/core/module.app.js",
                "mini": "gulliver/js/maborak/core/module.app.js",
                "minify": true
            },
            {
                "name": "module.rpc",
                "full": "gulliver/js/maborak/core/module.rpc.js",
                "mini": "gulliver/js/maborak/core/module.rpc.js",
                "minify": true
            },
            {
                "name": "module.fx",
                "full": "gulliver/js/maborak/core/module.fx.js",
                "mini": "gulliver/js/maborak/core/module.fx.js",
                "minify": true
            },
            {
                "name": "module.drag",
                "full": "gulliver/js/maborak/core/module.drag.js",
                "mini": "gulliver/js/maborak/core/module.drag.js",
                "minify": true
            },
            {
                "name": "module.drop",
                "full": "gulliver/js/maborak/core/module.drop.js",
                "mini": "gulliver/js/maborak/core/module.drop.js",
                "minify": true
            },
            {
                "name": "module.dom",
                "full": "gulliver/js/maborak/core/module.dom.js",
                "mini": "gulliver/js/maborak/core/module.dom.js",
                "minify": true
            },
            {
                "name": "module.abbr",
                "full": "gulliver/js/maborak/core/module.abbr.js",
                "mini": "gulliver/js/maborak/core/module.abbr.js",
                "minify": true
            },
            {
                "name": "module.dashboard",
                "full": "gulliver/js/maborak/core/module.dashboard.js",
                "mini": "gulliver/js/maborak/core/module.dashboard.js",
                "minify": true
            },
            {
                "name": "cases",
                "full": "workflow/engine/js/cases/core/cases.js",
                "mini": "workflow/engine/js/cases/core/cases.js",
                "minify": true
            },
            {
                "name": "cases_Step",
                "full": "workflow/engine/js/cases/core/cases_Step.js",
                "mini": "workflow/engine/js/cases/core/cases_Step.js",
                "minify": true
            },
            {
                "name": "processmap",
                "full": "workflow/engine/js/processmap/core/processmap.js",
                "mini": "workflow/engine/js/processmap/core/processmap.js",
                "minify": true
            },
            {
                "name": "appFolderList",
                "full": "workflow/engine/js/appFolder/core/appFolderList.js",
                "mini": "workflow/engine/js/appFolder/core/appFolderList.js",
                "minify": true
            },
            {
                "name": "editor",
                "full": "gulliver/thirdparty/htmlarea/editor.js",
                "mini": "gulliver/thirdparty/htmlarea/editor.js",
                "minify": true
            }
        ],
        "build" : true,
        "build_js_to" : "gulliver/js/maborak/core/"
    },
    {
        "name": "draw2d",
        "libraries": [
            {
                "name": "wz_jsgraphics",
                "full": "gulliver/js/ext/wz_jsgraphics.js",
                "mini": "gulliver/js/ext/wz_jsgraphics.js",
                "minify": true
            },
            {
                "name": "mootools",
                "full": "gulliver/js/ext/mootools.js",
                "mini": "gulliver/js/ext/mootools.js",
                "minify": true
            },
            {
                "name": "moocanvas",
                "full": "gulliver/js/ext/moocanvas.js",
                "mini": "gulliver/js/ext/moocanvas.js",
                "minify": true
            },
            {
                "name": "draw2d",
                "full": "gulliver/js/ext/draw2d.old.js",
                "mini": "gulliver/js/ext/draw2d.old.js",
                "minify": true
            }
        ],
        "build" : false,
        "build_js_to" : "gulliver/js/ext/"
    }
]